greenplanet_energy_api/__init__.py
greenplanet_energy_api/api.py
greenplanet_energy_api/exceptions.py
greenplanet_energy_api/py.typed
greenplanet_energy_api-0.1.2.dist-info/licenses/LICENSE
greenplanet_energy_api-0.1.2.dist-info/METADATA
greenplanet_energy_api-0.1.2.dist-info/WHEEL
greenplanet_energy_api-0.1.2.dist-info/top_level.txt
greenplanet_energy_api-0.1.2.dist-info/RECORD
