Metadata-Version: 2.4
Name: greenplanet-energy-api
Version: 0.1.2
Summary: Python API client for Green Planet Energy electricity pricing data
Author-email: Your Name <your.email@example.com>
Maintainer-email: Your Name <your.email@example.com>
License: MIT
Project-URL: Homepage, https://github.com/petschni/greenplanet-energy-api
Project-URL: Repository, https://github.com/petschni/greenplanet-energy-api
Project-URL: Issues, https://github.com/petschni/greenplanet-energy-api/issues
Project-URL: Changelog, https://github.com/petschni/greenplanet-energy-api/blob/main/CHANGELOG.md
Keywords: green planet energy,electricity prices,energy,api client,home assistant
Classifier: Development Status :: 4 - Beta
Classifier: Intended Audience :: Developers
Classifier: License :: OSI Approved :: MIT License
Classifier: Operating System :: OS Independent
Classifier: Programming Language :: Python :: 3
Classifier: Programming Language :: Python :: 3.11
Classifier: Programming Language :: Python :: 3.12
Classifier: Programming Language :: Python :: 3.13
Classifier: Topic :: Home Automation
Classifier: Topic :: Software Development :: Libraries :: Python Modules
Requires-Python: >=3.11
License-File: LICENSE
Requires-Dist: aiohttp>=3.8.0
Provides-Extra: dev
Requires-Dist: pytest>=7.0; extra == "dev"
Requires-Dist: pytest-asyncio>=0.21.0; extra == "dev"
Requires-Dist: pytest-aiohttp>=1.0.4; extra == "dev"
Requires-Dist: pytest-cov>=4.0; extra == "dev"
Requires-Dist: black>=23.0; extra == "dev"
Requires-Dist: ruff>=0.1.0; extra == "dev"
Requires-Dist: mypy>=1.0; extra == "dev"
Requires-Dist: aioresponses>=0.7.4; extra == "dev"
Dynamic: license-file
